Metadata-Version: 2.1
Name: djpdfview
Version: 1.0.0
Summary: Working with pdf made easy
Home-page: https://himelrana.com
Author: Himel
Author-email: contact@himelrana.com
License: MIT
Keywords: pdfview in django
Platform: UNKNOWN
Classifier: Development Status :: 5 - Production/Stable
Classifier: Intended Audience :: Developers
Classifier: Operating System :: Microsoft :: Windows :: Windows 10
Classifier: License :: OSI Approved :: MIT License
Classifier: Programming Language :: Python :: 3
Requires-Python: >=3.6
License-File: LICENCE.txt
